temporal_disaggregation/__init__.py
temporal_disaggregation/aggregation.py
temporal_disaggregation/disaggregation.py
temporal_disaggregation/processor.py
temporal_disaggregation/retropolation.py
temporal_disaggregation/utils.py
temporal_disaggregation-0.1.4.dist-info/METADATA
temporal_disaggregation-0.1.4.dist-info/WHEEL
temporal_disaggregation-0.1.4.dist-info/top_level.txt
temporal_disaggregation-0.1.4.dist-info/RECORD
