Metadata-Version: 2.2
Name: temporal_disaggregation
Version: 0.1.4
Summary: Library for time series temporal disaggregation
Home-page: https://github.com/jaimevera1107/temporal-disaggregation
Author: Jaime Vera
Author-email: Jaime Vera-Jaramillo <jaimevera1107@gmail.com>
Requires-Python: >=3.7
Requires-Dist: numpy
Requires-Dist: pandas
Requires-Dist: scipy
Requires-Dist: matplotlib
Requires-Dist: scikit-learn
Dynamic: author
Dynamic: home-page
Dynamic: requires-python
